mcp_server_duckdb/__init__.py
mcp_server_duckdb/config.py
mcp_server_duckdb/server.py
iflow_mcp_mcp_server_duckdb-1.1.0.dist-info/METADATA
iflow_mcp_mcp_server_duckdb-1.1.0.dist-info/WHEEL
iflow_mcp_mcp_server_duckdb-1.1.0.dist-info/entry_points.txt
iflow_mcp_mcp_server_duckdb-1.1.0.dist-info/licenses/LICENSE
iflow_mcp_mcp_server_duckdb-1.1.0.dist-info/RECORD
