Metadata-Version: 2.4
Name: iflow-mcp_mcp-server-duckdb
Version: 1.1.0
Summary: A DuckDB MCP server
Project-URL: Homepage, https://github.com/ktanaka101/mcp-server-duckdb
Project-URL: Bug Tracker, https://github.com/ktanaka101/mcp-server-duckdb/issues
Author-email: ktanaka101 <kentanaka101@gmail.com>
License: The MIT License (MIT)
License-File: LICENSE
Classifier: License :: OSI Approved :: MIT License
Classifier: Operating System :: OS Independent
Classifier: Programming Language :: Python :: 3
Classifier: Programming Language :: Python :: 3.10
Classifier: Programming Language :: Python :: 3.11
Classifier: Programming Language :: Python :: 3.12
Classifier: Programming Language :: Python :: 3.13
Classifier: Programming Language :: Python :: 3.14
Requires-Python: >=3.10
Requires-Dist: duckdb>=1.1.3
Requires-Dist: mcp>=1.0.0
